{
  "generated_at": "2025-12-29T20:23:42.910Z",
  "league": {
    "name": "The League of Ordinary Gentlemen",
    "status": "complete",
    "metadata": {
      "auto_continue": "on",
      "continued": "yes",
      "keeper_deadline": "0",
      "latest_league_winner_roster_id": "7",
      "trophy_loser": "loser3",
      "trophy_loser_background": "poop",
      "trophy_loser_banner_text": "LOWER BRACKET"
    },
    "settings": {
      "best_ball": 0,
      "last_report": 14,
      "waiver_budget": 500,
      "disable_adds": 0,
      "capacity_override": 0,
      "taxi_deadline": 0,
      "draft_rounds": 5,
      "reserve_allow_na": 1,
      "start_week": 1,
      "playoff_seed_type": 0,
      "playoff_teams": 6,
      "veto_votes_needed": 5,
      "squads": 1,
      "num_teams": 10,
      "daily_waivers_hour": 1,
      "playoff_type": 1,
      "taxi_slots": 5,
      "last_scored_leg": 17,
      "daily_waivers_days": 5461,
      "playoff_week_start": 15,
      "waiver_clear_days": 2,
      "reserve_allow_doubtful": 0,
      "commissioner_direct_invite": 0,
      "veto_auto_poll": 0,
      "reserve_allow_dnr": 1,
      "taxi_allow_vets": 0,
      "waiver_day_of_week": 2,
      "playoff_round_type": 0,
      "reserve_allow_out": 1,
      "reserve_allow_sus": 1,
      "veto_show_votes": 0,
      "trade_deadline": 13,
      "taxi_years": 1,
      "daily_waivers": 1,
      "disable_trades": 0,
      "pick_trading": 1,
      "type": 2,
      "max_keepers": 1,
      "waiver_type": 2,
      "league_average_match": 0,
      "trade_review_days": 0,
      "bench_lock": 0,
      "offseason_adds": 0,
      "leg": 17,
      "daily_waivers_base": 4,
      "reserve_slots": 5,
      "reserve_allow_cov": 1,
      "daily_waivers_last_ran": 2
    },
    "avatar": null,
    "company_id": null,
    "last_message_id": "1048251349030375424",
    "shard": 503,
    "season": "2023",
    "season_type": "regular",
    "sport": "nfl",
    "scoring_settings": {
      "sack": 0,
      "fgm_40_49": 0,
      "pass_int": -2,
      "pts_allow_0": 0,
      "pass_2pt": 2,
      "st_td": 0,
      "fgm_yds_over_30": 0.10000000149011612,
      "rec_td": 6,
      "fgm_30_39": 0,
      "xpmiss": -1,
      "rush_td": 6,
      "fgm": 3,
      "rec_2pt": 2,
      "st_fum_rec": 0,
      "fgmiss": 0,
      "ff": 0,
      "fgmiss_30_39": -1,
      "rec": 0.5,
      "pts_allow_14_20": 0,
      "fgm_0_19": 0,
      "int": 0,
      "def_st_fum_rec": 0,
      "fum_lost": -2,
      "pts_allow_1_6": 0,
      "fgmiss_20_29": -2,
      "fgm_20_29": 0,
      "pts_allow_21_27": 0,
      "xpm": 1,
      "fgmiss_0_19": -3,
      "rush_2pt": 2,
      "fum_rec": 0,
      "def_st_td": 0,
      "fgm_50p": 0,
      "def_td": 0,
      "safe": 0,
      "pass_yd": 0.03999999910593033,
      "blk_kick": 0,
      "pass_td": 4,
      "rush_yd": 0.10000000149011612,
      "fum": -1,
      "pts_allow_28_34": 0,
      "pts_allow_35p": 0,
      "fum_rec_td": 6,
      "rec_yd": 0.10000000149011612,
      "def_st_ff": 0,
      "pts_allow_7_13": 0,
      "st_ff": 0
    },
    "draft_id": "917460390425059329",
    "last_author_avatar": "924cccc6a25bc852cd24163b72dd1b49",
    "last_author_display_name": "Davideo",
    "last_author_id": "396509942258876416",
    "last_author_is_bot": false,
    "last_message_attachment": null,
    "last_message_text_map": null,
    "last_message_time": 1704285106479,
    "last_pinned_message_id": null,
    "last_read_id": null,
    "league_id": "917460390425059328",
    "previous_league_id": "803754961279225856",
    "group_id": null,
    "bracket_id": 1045843260666630100,
    "bracket_overrides_id": null,
    "loser_bracket_id": 1045843260670824400,
    "loser_bracket_overrides_id": null,
    "roster_positions": [
      "QB",
      "RB",
      "RB",
      "WR",
      "WR",
      "WR",
      "TE",
      "FLEX",
      "FLEX",
      "K",
      "BN",
      "BN",
      "BN",
      "BN",
      "BN",
      "BN",
      "BN",
      "BN",
      "BN",
      "BN",
      "BN",
      "BN",
      "BN",
      "BN",
      "BN",
      "BN",
      "BN",
      "BN",
      "BN",
      "BN"
    ],
    "total_rosters": 10
  },
  "users": [
    {
      "avatar": "4ba072e6248388d12d79bfee723b9155",
      "display_name": "BMRoberson",
      "is_bot": null,
      "is_owner": true,
      "league_id": "917460390425059328",
      "metadata": {
        "allow_pn": "on",
        "avatar": "https://sleepercdn.com/uploads/6af1b152c0e047c3873af8efbd463d48",
        "mascot_item_type_id_leg_1": "titan-up",
        "mascot_item_type_id_leg_10": "champion-ship",
        "mascot_item_type_id_leg_11": "champion-ship",
        "mascot_item_type_id_leg_12": "champion-ship",
        "mascot_item_type_id_leg_13": "champion-ship",
        "mascot_item_type_id_leg_14": "champion-ship",
        "mascot_item_type_id_leg_15": "champion-ship",
        "mascot_item_type_id_leg_16": "champion-ship",
        "mascot_item_type_id_leg_17": "champion-ship",
        "mascot_item_type_id_leg_18": "champion-ship",
        "mascot_item_type_id_leg_2": "titan-up",
        "mascot_item_type_id_leg_3": "titan-up",
        "mascot_item_type_id_leg_4": "titan-up",
        "mascot_item_type_id_leg_5": "titan-up",
        "mascot_item_type_id_leg_6": "titan-up",
        "mascot_item_type_id_leg_7": "titan-up",
        "mascot_item_type_id_leg_8": "titan-up",
        "mascot_item_type_id_leg_9": "champion-ship",
        "mascot_message_emotion_leg_1": "dancing",
        "mascot_message_emotion_leg_9": "victory",
        "mention_pn": "on",
        "team_name": "FireDrakes"
      },
      "settings": null,
      "user_id": "80740998057443328"
    },
    {
      "avatar": "f7533d91121bdaf9ab3428413f0884dc",
      "display_name": "citizenmiller",
      "is_bot": false,
      "is_owner": false,
      "league_id": "917460390425059328",
      "metadata": {
        "allow_pn": "on",
        "mention_pn": "on",
        "show_mascots": "off",
        "team_name": "Headhunters"
      },
      "settings": null,
      "user_id": "209840797237907456"
    },
    {
      "avatar": "970bdfbe26e79148fa3fd45284afd11f",
      "display_name": "amandajroberson",
      "is_bot": false,
      "is_owner": false,
      "league_id": "917460390425059328",
      "metadata": {
        "allow_pn": "on",
        "join_voice_pn": "off",
        "mascot_message": "off",
        "mention_pn": "on",
        "player_like_pn": "off",
        "player_nickname_update": "off",
        "team_name": "A Team Has No Name",
        "team_name_update": "off",
        "trade_block_pn": "off",
        "transaction_commissioner": "off",
        "transaction_free_agent": "off",
        "transaction_trade": "off",
        "transaction_waiver": "off",
        "user_message_pn": "on"
      },
      "settings": null,
      "user_id": "390203107897827328"
    },
    {
      "avatar": "505e2c7bf00ea8f5286276afda84205c",
      "display_name": "MelKiperSr",
      "is_bot": false,
      "is_owner": false,
      "league_id": "917460390425059328",
      "metadata": {
        "allow_pn": "on",
        "mention_pn": "on"
      },
      "settings": null,
      "user_id": "390274014192336896"
    },
    {
      "avatar": "924cccc6a25bc852cd24163b72dd1b49",
      "display_name": "Davideo",
      "is_bot": false,
      "is_owner": false,
      "league_id": "917460390425059328",
      "metadata": {
        "allow_pn": "on",
        "archived": "off",
        "mention_pn": "on",
        "show_mascots": "off",
        "team_name": "Pork-Chop Express"
      },
      "settings": null,
      "user_id": "396509942258876416"
    },
    {
      "avatar": "1fe089e517448d9fe207b8607ca8e81b",
      "display_name": "ErictheRed3",
      "is_bot": false,
      "is_owner": false,
      "league_id": "917460390425059328",
      "metadata": {
        "allow_pn": "on",
        "mascot_item_type_id_leg_13": "titan-up",
        "team_name_update": "on",
        "join_voice_pn": "on",
        "transaction_free_agent": "on",
        "mascot_item_type_id_leg_17": "titan-up",
        "mascot_item_type_id_leg_12": "titan-up",
        "mascot_item_type_id_leg_1": "titan-up",
        "player_like_pn": "on",
        "mascot_item_type_id_leg_9": "titan-up",
        "mascot_item_type_id_leg_4": "titan-up",
        "transaction_commissioner": "on",
        "mascot_item_type_id_leg_3": "titan-up",
        "mascot_item_type_id_leg_18": "titan-up",
        "mascot_item_type_id_leg_10": "titan-up",
        "mascot_item_type_id_leg_5": "titan-up",
        "mascot_message": "on",
        "trade_block_pn": "on",
        "mascot_item_type_id_leg_7": "titan-up",
        "mascot_item_type_id_leg_14": "titan-up",
        "mascot_item_type_id_leg_6": "titan-up",
        "user_message_pn": "on",
        "mascot_item_type_id_leg_11": "titan-up",
        "mascot_item_type_id_leg_2": "titan-up",
        "mention_pn": "on",
        "player_nickname_update": "on",
        "transaction_waiver": "on",
        "mascot_item_type_id_leg_15": "titan-up",
        "mascot_message_emotion_leg_1": "idle",
        "team_name": "Marauders",
        "mascot_item_type_id_leg_8": "titan-up",
        "avatar": "https://sleepercdn.com/uploads/381cbc94932a7299c85e484d30673d61.jpg",
        "mascot_item_type_id_leg_16": "titan-up",
        "transaction_trade": "on"
      },
      "settings": null,
      "user_id": "400481558605144064"
    },
    {
      "avatar": "41d0904183c2fffbc34f65daa489183d",
      "display_name": "mydadysnotayeti",
      "is_bot": false,
      "is_owner": false,
      "league_id": "917460390425059328",
      "metadata": {
        "allow_pn": "on",
        "mascot_item_type_id_leg_1": "philly-special",
        "mascot_item_type_id_leg_10": "trash",
        "mascot_item_type_id_leg_11": "trash",
        "mascot_item_type_id_leg_12": "trash",
        "mascot_item_type_id_leg_13": "trash",
        "mascot_item_type_id_leg_14": "trash",
        "mascot_item_type_id_leg_15": "trash",
        "mascot_item_type_id_leg_16": "trash",
        "mascot_item_type_id_leg_17": "trash",
        "mascot_item_type_id_leg_18": "trash",
        "mascot_item_type_id_leg_2": "trash",
        "mascot_item_type_id_leg_3": "trash",
        "mascot_item_type_id_leg_4": "trash",
        "mascot_item_type_id_leg_5": "trash",
        "mascot_item_type_id_leg_6": "trash",
        "mascot_item_type_id_leg_7": "trash",
        "mascot_item_type_id_leg_8": "trash",
        "mascot_item_type_id_leg_9": "trash",
        "mascot_message_emotion_leg_1": "taunting",
        "mascot_message_emotion_leg_2": "taunting",
        "mascot_message_emotion_leg_4": "taunting",
        "mention_pn": "on"
      },
      "settings": null,
      "user_id": "403029199528394752"
    },
    {
      "avatar": "d74ae2680051068f29cea58e71dec141",
      "display_name": "AAronRob44",
      "is_bot": false,
      "is_owner": false,
      "league_id": "917460390425059328",
      "metadata": {
        "allow_pn": "on",
        "allow_sms": "on",
        "avatar": "https://sleepercdn.com/uploads/29d7374022327b8689e51443de751450.jpg",
        "mascot_item_type_id_leg_1": "pizza",
        "mascot_item_type_id_leg_10": "pizza",
        "mascot_item_type_id_leg_11": "pizza",
        "mascot_item_type_id_leg_12": "pizza",
        "mascot_item_type_id_leg_13": "pizza",
        "mascot_item_type_id_leg_14": "pizza",
        "mascot_item_type_id_leg_15": "pizza",
        "mascot_item_type_id_leg_16": "pizza",
        "mascot_item_type_id_leg_17": "pizza",
        "mascot_item_type_id_leg_18": "pizza",
        "mascot_item_type_id_leg_2": "pizza",
        "mascot_item_type_id_leg_3": "pizza",
        "mascot_item_type_id_leg_4": "pizza",
        "mascot_item_type_id_leg_5": "pizza",
        "mascot_item_type_id_leg_6": "pizza",
        "mascot_item_type_id_leg_7": "pizza",
        "mascot_item_type_id_leg_8": "pizza",
        "mascot_item_type_id_leg_9": "pizza",
        "mascot_message_emotion_leg_1": "victory",
        "mention_pn": "on",
        "team_name": "Nightvale Scorpions"
      },
      "settings": null,
      "user_id": "405012631083089920"
    },
    {
      "avatar": "47579ddabd2d9245934bc85d61b10e9a",
      "display_name": "Smelt",
      "is_bot": false,
      "is_owner": false,
      "league_id": "917460390425059328",
      "metadata": {
        "allow_sms": "on",
        "allow_pn": "on",
        "mascot_item_type_id_leg_13": "trash",
        "team_name_update": "off",
        "join_voice_pn": "on",
        "transaction_free_agent": "off",
        "mascot_item_type_id_leg_17": "trash",
        "mascot_item_type_id_leg_12": "trash",
        "mascot_item_type_id_leg_1": "trash",
        "player_like_pn": "on",
        "mascot_item_type_id_leg_9": "trash",
        "mascot_item_type_id_leg_4": "trash",
        "show_mascots": "on",
        "transaction_commissioner": "on",
        "mascot_item_type_id_leg_3": "trash",
        "mascot_item_type_id_leg_18": "trash",
        "mascot_item_type_id_leg_10": "trash",
        "mascot_item_type_id_leg_5": "trash",
        "mascot_message": "off",
        "trade_block_pn": "on",
        "mascot_item_type_id_leg_7": "trash",
        "mascot_item_type_id_leg_14": "trash",
        "mascot_item_type_id_leg_6": "trash",
        "user_message_pn": "off",
        "mascot_item_type_id_leg_11": "trash",
        "mascot_item_type_id_leg_2": "trash",
        "mention_pn": "on",
        "player_nickname_update": "off",
        "transaction_waiver": "on",
        "mascot_item_type_id_leg_15": "trash",
        "mascot_message_emotion_leg_1": "idle",
        "team_name": "Alpha Males",
        "mascot_item_type_id_leg_8": "trash",
        "avatar": "https://sleepercdn.com/uploads/57aa1aae81df35d18e8f605278f3da73.jpg",
        "mascot_item_type_id_leg_16": "trash",
        "transaction_trade": "on"
      },
      "settings": null,
      "user_id": "405178981927632896"
    },
    {
      "avatar": "1fe089e517448d9fe207b8607ca8e81b",
      "display_name": "monstrhuntr",
      "is_bot": false,
      "is_owner": false,
      "league_id": "917460390425059328",
      "metadata": {
        "allow_pn": "on",
        "allow_sms": "on",
        "mention_pn": "on"
      },
      "settings": null,
      "user_id": "415889284776611840"
    }
  ],
  "rosters": [
    {
      "co_owners": null,
      "keepers": null,
      "league_id": "917460390425059328",
      "metadata": {
        "allow_pn_news": "on",
        "allow_pn_scoring": "on",
        "p_nick_1234": "Team Captain",
        "p_nick_1408": "OTB",
        "p_nick_1466": "Team Captain",
        "p_nick_2374": "",
        "p_nick_2391": "OTB",
        "record": "LWWLLWLLWWLWWL",
        "streak": "1L"
      },
      "owner_id": "80740998057443328",
      "player_map": null,
      "players": [
        "8188",
        "6813",
        "5846",
        "4033",
        "9495",
        "5850",
        "9497",
        "7602",
        "9754",
        "11199",
        "8121",
        "11306",
        "6845",
        "8151",
        "1234",
        "9221",
        "10866",
        "4179",
        "2374",
        "8676",
        "2309",
        "8225",
        "9511",
        "7596",
        "7021",
        "4137",
        "2133",
        "10859",
        "4046",
        "8131",
        "10232",
        "4666",
        "9488",
        "4227",
        "8111",
        "7828",
        "6918"
      ],
      "reserve": [
        "6918",
        "9511"
      ],
      "roster_id": 1,
      "settings": {
        "fpts": 1619,
        "fpts_against": 1559,
        "fpts_against_decimal": 2,
        "fpts_decimal": 54,
        "losses": 7,
        "ppts": 2057,
        "ppts_decimal": 8,
        "rank": 4,
        "ties": 0,
        "total_moves": 0,
        "waiver_budget_used": 283,
        "waiver_position": 7,
        "wins": 7
      },
      "starters": [
        "4046",
        "9221",
        "6813",
        "2374",
        "5846",
        "2133",
        "10859",
        "4137",
        "8151",
        "4227"
      ],
      "taxi": [
        "10866",
        "8131",
        "9488",
        "9495",
        "9497"
      ]
    },
    {
      "co_owners": null,
      "keepers": null,
      "league_id": "917460390425059328",
      "metadata": {
        "p_nick_4984": "Real Goat",
        "p_nick_6822": "",
        "record": "WWLWWLWLLWWWLW",
        "streak": "1W"
      },
      "owner_id": "209840797237907456",
      "player_map": null,
      "players": [
        "3242",
        "5000",
        "6814",
        "650",
        "4984",
        "6011",
        "7611",
        "7757",
        "6826",
        "4381",
        "8153",
        "1689",
        "10219",
        "6920",
        "4066",
        "5916",
        "10213",
        "2216",
        "3321",
        "7694",
        "1535",
        "8167",
        "5347",
        "4111",
        "6801",
        "8125",
        "1339",
        "7561",
        "6130",
        "1266",
        "8119",
        "8138",
        "8134"
      ],
      "reserve": [
        "5347",
        "6814",
        "7611"
      ],
      "roster_id": 2,
      "settings": {
        "fpts": 1558,
        "fpts_against": 1507,
        "fpts_against_decimal": 0,
        "fpts_decimal": 2,
        "losses": 5,
        "ppts": 2070,
        "ppts_decimal": 6,
        "rank": 3,
        "ties": 0,
        "total_moves": 0,
        "waiver_budget_used": 0,
        "waiver_position": 1,
        "wins": 9
      },
      "starters": [
        "4984",
        "6130",
        "8138",
        "3321",
        "6801",
        "2216",
        "6826",
        "4066",
        "1689",
        "650"
      ],
      "taxi": [
        "10213",
        "10219",
        "8125",
        "8134",
        "8153"
      ]
    },
    {
      "co_owners": null,
      "keepers": null,
      "league_id": "917460390425059328",
      "metadata": {
        "allow_pn_scoring": "on",
        "record": "LWLWWWLWLLWWLL",
        "streak": "2L"
      },
      "owner_id": "415889284776611840",
      "player_map": null,
      "players": [
        "2251",
        "8155",
        "7002",
        "5095",
        "2307",
        "10235",
        "8168",
        "9224",
        "8150",
        "8159",
        "6943",
        "4080",
        "8112",
        "6234",
        "9226",
        "5022",
        "8171",
        "8130",
        "5119",
        "4034",
        "9479",
        "8160",
        "10226",
        "8253",
        "8135",
        "6659",
        "10862",
        "9486",
        "1049",
        "8147",
        "5284",
        "6768",
        "6790",
        "7585",
        "6783"
      ],
      "reserve": null,
      "roster_id": 3,
      "settings": {
        "fpts": 1558,
        "fpts_against": 1378,
        "fpts_against_decimal": 30,
        "fpts_decimal": 40,
        "losses": 7,
        "ppts": 1927,
        "ppts_decimal": 68,
        "rank": 7,
        "ties": 0,
        "total_moves": 0,
        "waiver_budget_used": 207,
        "waiver_position": 4,
        "wins": 7
      },
      "starters": [
        "6768",
        "4034",
        "6790",
        "6943",
        "4080",
        "8112",
        "5022",
        "8150",
        "9226",
        "5119"
      ],
      "taxi": [
        "10235",
        "8159",
        "9224",
        "9479",
        "9486"
      ]
    },
    {
      "co_owners": null,
      "keepers": null,
      "league_id": "917460390425059328",
      "metadata": {
        "allow_pn_scoring": "on",
        "record": "WLLWLLWLWLLLLW",
        "restrict_pn_scoring_starters_only": "on",
        "streak": "1W"
      },
      "owner_id": "390203107897827328",
      "player_map": null,
      "players": [
        "6828",
        "5849",
        "5374",
        "7527",
        "5880",
        "6151",
        "2505",
        "4149",
        "3969",
        "9482",
        "4089",
        "3200",
        "9997",
        "4198",
        "5980",
        "6794",
        "8123",
        "5915",
        "4199",
        "2028",
        "8118",
        "11292",
        "7525",
        "4983",
        "17",
        "7045",
        "9493",
        "9220",
        "7535",
        "8223",
        "4040",
        "4195",
        "5870",
        "4943",
        "8136"
      ],
      "reserve": [
        "5870"
      ],
      "roster_id": 4,
      "settings": {
        "fpts": 1517,
        "fpts_against": 1649,
        "fpts_against_decimal": 8,
        "fpts_decimal": 80,
        "losses": 9,
        "ppts": 1792,
        "ppts_decimal": 40,
        "rank": 8,
        "ties": 0,
        "total_moves": 0,
        "waiver_budget_used": 40,
        "waiver_position": 8,
        "wins": 5
      },
      "starters": [
        "5849",
        "8136",
        "4199",
        "9493",
        "7525",
        "6794",
        "2505",
        "4983",
        "9997",
        "4195"
      ],
      "taxi": [
        "8118",
        "8123",
        "8223",
        "9220"
      ]
    },
    {
      "co_owners": null,
      "keepers": null,
      "league_id": "917460390425059328",
      "metadata": {
        "allow_pn_scoring": "on",
        "record": "LWWLWWLWLLLLWL",
        "restrict_pn_scoring_starters_only": "on",
        "streak": "1L"
      },
      "owner_id": "400481558605144064",
      "player_map": null,
      "players": [
        "7922",
        "9753",
        "8139",
        "5113",
        "7594",
        "9492",
        "9222",
        "3202",
        "5857",
        "4951",
        "8219",
        "7543",
        "6951",
        "7090",
        "8148",
        "2749",
        "1992",
        "4973",
        "6886",
        "3164",
        "5967",
        "5937",
        "6694",
        "5110",
        "8146",
        "8137",
        "9506",
        "10937",
        "8205",
        "6804",
        "1348",
        "7538",
        "6904",
        "7601",
        "7606",
        "3294",
        "7553",
        "11439"
      ],
      "reserve": [
        "5110",
        "6951",
        "8219"
      ],
      "roster_id": 5,
      "settings": {
        "fpts": 1594,
        "fpts_against": 1716,
        "fpts_against_decimal": 38,
        "fpts_decimal": 84,
        "losses": 8,
        "ppts": 1983,
        "ppts_decimal": 16,
        "rank": 6,
        "ties": 0,
        "total_moves": 0,
        "waiver_budget_used": 16,
        "waiver_position": 2,
        "wins": 6
      },
      "starters": [
        "6904",
        "5967",
        "7543",
        "8146",
        "8137",
        "5937",
        "7553",
        "7594",
        "2749",
        "10937"
      ],
      "taxi": [
        "11439",
        "9222",
        "9492",
        "9506",
        "9753"
      ]
    },
    {
      "co_owners": null,
      "keepers": null,
      "league_id": "917460390425059328",
      "metadata": {
        "allow_pn_news": "off",
        "allow_pn_scoring": "off",
        "record": "WLWLWLWWWLWLWW",
        "streak": "2W"
      },
      "owner_id": "390274014192336896",
      "player_map": null,
      "players": [
        "2325",
        "6989",
        "4017",
        "8140",
        "4035",
        "8162",
        "6853",
        "7600",
        "7670",
        "4018",
        "4950",
        "2449",
        "11058",
        "2078",
        "1352",
        "4217",
        "10444",
        "7610",
        "10857",
        "5955",
        "3214",
        "4866",
        "3271",
        "8211",
        "96",
        "7587",
        "5185",
        "1166",
        "8259",
        "9998",
        "6820",
        "7049",
        "421",
        "3423",
        "6786"
      ],
      "reserve": [
        "1166",
        "4017",
        "7610",
        "96"
      ],
      "roster_id": 6,
      "settings": {
        "fpts": 1576,
        "fpts_against": 1568,
        "fpts_against_decimal": 26,
        "fpts_decimal": 82,
        "losses": 5,
        "ppts": 2005,
        "ppts_decimal": 58,
        "rank": 2,
        "ties": 0,
        "total_moves": 0,
        "waiver_budget_used": 0,
        "waiver_position": 3,
        "wins": 9
      },
      "starters": [
        "421",
        "4866",
        "4018",
        "2449",
        "6786",
        "2078",
        "4217",
        "6820",
        "4035",
        "11058"
      ],
      "taxi": [
        "10444",
        "10857",
        "8162",
        "9998"
      ]
    },
    {
      "co_owners": null,
      "keepers": null,
      "league_id": "917460390425059328",
      "metadata": {
        "record": "WLWWLWWWLWWWWW",
        "streak": "5W"
      },
      "owner_id": "396509942258876416",
      "player_map": null,
      "players": [
        "4029",
        "11114",
        "6149",
        "10863",
        "7042",
        "5045",
        "8172",
        "6803",
        "8144",
        "8230",
        "5890",
        "10218",
        "5046",
        "9508",
        "7547",
        "1264",
        "3163",
        "9229",
        "5133",
        "5917",
        "7523",
        "4068",
        "4455",
        "5859",
        "8143",
        "3198",
        "6421",
        "2161",
        "4663",
        "5973",
        "4988",
        "9501",
        "6797",
        "10867",
        "8110",
        "5844",
        "2197",
        "11311",
        "7593",
        "19"
      ],
      "reserve": [
        "4068",
        "4988",
        "6797",
        "8172",
        "9229"
      ],
      "roster_id": 7,
      "settings": {
        "fpts": 1749,
        "fpts_against": 1524,
        "fpts_against_decimal": 2,
        "fpts_decimal": 88,
        "losses": 3,
        "ppts": 2101,
        "ppts_decimal": 88,
        "rank": 1,
        "ties": 0,
        "total_moves": 0,
        "waiver_budget_used": 300,
        "waiver_position": 10,
        "wins": 11
      },
      "starters": [
        "3163",
        "3198",
        "4663",
        "5859",
        "7547",
        "8144",
        "8110",
        "8230",
        "6803",
        "1264"
      ],
      "taxi": [
        "10218",
        "10863",
        "10867",
        "11311",
        "9501"
      ]
    },
    {
      "co_owners": null,
      "keepers": null,
      "league_id": "917460390425059328",
      "metadata": {
        "allow_pn_inactive_starters": "on",
        "allow_pn_player_injury_status": "on",
        "allow_pn_scoring": "on",
        "record": "LLWLLLLLWWLWLL",
        "restrict_pn_scoring_starters_only": "on",
        "streak": "2L"
      },
      "owner_id": "405178981927632896",
      "player_map": null,
      "players": [
        "4234",
        "5001",
        "9505",
        "5086",
        "9758",
        "10871",
        "8126",
        "4144",
        "6938",
        "2319",
        "9225",
        "7571",
        "6824",
        "7567",
        "4147",
        "7565",
        "8183",
        "1479",
        "9494",
        "10229",
        "8221",
        "10225",
        "8142",
        "7591",
        "4171",
        "7562",
        "7607",
        "8145",
        "4892",
        "7839",
        "5906",
        "3225",
        "10222",
        "10228",
        "8116"
      ],
      "reserve": [
        "6938"
      ],
      "roster_id": 8,
      "settings": {
        "fpts": 1267,
        "fpts_against": 1500,
        "fpts_against_decimal": 34,
        "fpts_decimal": 76,
        "losses": 10,
        "ppts": 1690,
        "ppts_decimal": 86,
        "rank": 10,
        "ties": 0,
        "total_moves": 0,
        "waiver_budget_used": 27,
        "waiver_position": 5,
        "wins": 4
      },
      "starters": [
        "7591",
        "7567",
        "4147",
        "2319",
        "10229",
        "3225",
        "5001",
        "5086",
        "4234",
        "7839"
      ],
      "taxi": [
        "10871",
        "8145",
        "9225",
        "9505"
      ]
    },
    {
      "co_owners": null,
      "keepers": null,
      "league_id": "917460390425059328",
      "metadata": {
        "p_nick_8258": "New Jersey",
        "record": "WWLLLWWWLWLLLW",
        "p_nick_6149": "Darius Sleepton",
        "p_nick_5848": "Hollywood",
        "p_nick_1077": "Fat Travi ",
        "p_nick_5892": "D Money",
        "p_nick_1944": "My boy blue",
        "p_nick_6011": "Secret Garden",
        "p_nick_7546": "A Crook",
        "p_nick_4037": "Christian",
        "p_nick_1837": "Jimmy G",
        "p_nick_8202": "Mike",
        "p_nick_4131": "Kenny G",
        "p_nick_6156": "Gale the Snell",
        "p_nick_7569": "Nitro Collins",
        "p_nick_7612": "The Wayne",
        "p_nick_4039": "Kupper Coop",
        "p_nick_4157": "Cohen Brothers",
        "p_nick_6130": "Devin Always Singletary",
        "p_nick_5046": "Garbage",
        "p_nick_6847": "Duvet Cover",
        "p_nick_6823": "Pretty Boy Jake",
        "p_nick_2024": "Charzard",
        "p_nick_8154": "The Commish",
        "p_nick_2711": "The Backup",
        "p_nick_5970": "Old Man Greg",
        "p_nick_6819": "Mike Pittboy",
        "p_nick_7066": "Kirks Friend",
        "p_nick_5919": "Drop Next",
        "p_nick_6088": "Bisi Jojo",
        "p_nick_391": "Soups-on",
        "p_nick_4151": "Butt",
        "p_nick_5007": "Keke Do You Love Me",
        "p_nick_6806": "Johnathan Killanger",
        "p_nick_4054": "Big Mo",
        "p_nick_8489": "Ogletree Insurance",
        "p_nick_4622": "Crappy Dede",
        "p_nick_1971": "Chickenpox",
        "p_nick_4972": "Red Nose",
        "p_nick_4985": "1 Cent",
        "p_nick_4152": "Big Mac",
        "p_nick_8129": "Demon Prince",
        "p_nick_6032": "Keelan Boss",
        "p_nick_4068": "Gonna Be Good Eventually",
        "p_nick_4273": "Chris Broken Hip and Kneck",
        "p_nick_1984": "Allen",
        "streak": "1W",
        "p_nick_6845": "Pricey Handcuff",
        "p_nick_4881": "A Running Back",
        "p_nick_5947": "Fake Kobi",
        "p_nick_5038": "Break a leg Cedee",
        "p_nick_3327": "A.C. ",
        "p_nick_6931": "DJ Houston",
        "p_nick_3657": "Fat Rob",
        "p_nick_6918": "Cure for the Itch",
        "p_nick_4147": "Pain Bot",
        "p_nick_6271": "Zach’ O’",
        "p_nick_7526": "Penguin",
        "p_nick_6843": "Al Borland",
        "p_nick_5872": "Samuel L. Deebo",
        "p_nick_5012": "Mark Mandrews",
        "p_nick_7703": "Ugly Man Jake ",
        "p_nick_7588": "Future",
        "p_nick_1433": "Praying Mantus",
        "p_nick_7496": "Lil Dede",
        "p_nick_3209": "Bookworm",
        "p_nick_5022": "Houston",
        "p_nick_2214": "Cameron Grate",
        "p_nick_6820": "1.1",
        "p_nick_5026": "Tre’Quandre Smith",
        "p_nick_6650": "The Kicker",
        "p_nick_5076": "R Kelly",
        "p_nick_4146": "Dede are you Riding",
        "p_nick_6768": "Spare Ribs",
        "p_nick_58": "Old Man Greg",
        "p_nick_6528": "Slye Fox"
      },
      "owner_id": "405012631083089920",
      "player_map": null,
      "players": [
        "7588",
        "6806",
        "6819",
        "5409",
        "9756",
        "1433",
        "5970",
        "9500",
        "8202",
        "5012",
        "8228",
        "9757",
        "5892",
        "8129",
        "9481",
        "7612",
        "5985",
        "4039",
        "5848",
        "9509",
        "6869",
        "6847",
        "9228",
        "7569",
        "5947",
        "9999",
        "5872",
        "4881",
        "1837",
        "7066",
        "4037",
        "8154",
        "7526",
        "5026",
        "5038",
        "9487",
        "11533"
      ],
      "reserve": [
        "5012",
        "6806",
        "8202",
        "9481"
      ],
      "roster_id": 9,
      "settings": {
        "fpts": 1602,
        "fpts_against": 1546,
        "fpts_against_decimal": 66,
        "fpts_decimal": 58,
        "losses": 7,
        "ppts": 2185,
        "ppts_decimal": 14,
        "rank": 5,
        "ties": 0,
        "total_moves": 0,
        "waiver_budget_used": 100,
        "waiver_position": 9,
        "wins": 7
      },
      "starters": [
        "4881",
        "9509",
        "7588",
        "5872",
        "4039",
        "6819",
        "5409",
        "7526",
        "5892",
        "11533"
      ],
      "taxi": [
        "8228",
        "9487",
        "9500",
        "9757"
      ]
    },
    {
      "co_owners": null,
      "keepers": null,
      "league_id": "917460390425059328",
      "metadata": {
        "record": "LLLWWLLLWLWLWL",
        "p_nick_616": "Avatar ",
        "p_nick_2078": "OBJ",
        "p_nick_1945": "Bos",
        "p_nick_4082": "Cupid",
        "p_nick_1911": "WS4",
        "p_nick_3309": "Wendell Tinydong",
        "p_nick_642": "Showtime",
        "allow_pn_scoring": "off",
        "p_nick_1567": "Pocket Rocket",
        "p_nick_2452": "J-Train",
        "p_nick_1979": "The B.O.A.T",
        "p_nick_3355": "Codecore",
        "p_nick_246": "Little Tank",
        "p_nick_4651": "C Ment",
        "p_nick_2306": "Crablegs",
        "p_nick_5136": "Jay Ads",
        "allow_pn_news": "off",
        "p_nick_2463": "The Outlaw ",
        "p_nick_954": "Supercam",
        "p_nick_949": "Jacuzzi ",
        "p_nick_5139": "3Q",
        "p_nick_322": "Mr. Clutch",
        "streak": "1L",
        "p_nick_745": "Beast Mode",
        "p_nick_2161": "Jay Mac",
        "p_nick_5052": "RJ2",
        "p_nick_5012": "Mandrews",
        "p_nick_4195": "Jake The Make",
        "p_nick_23": "Discount Tony Romo",
        "p_nick_1555": "Keenny",
        "p_nick_147": "DJ",
        "p_nick_1195": "Muscle Hamster",
        "p_nick_2182": "The Incredible Bulk",
        "p_nick_232": "The Inconvenient Truth ",
        "p_nick_188": "Noodle Arm",
        "p_nick_943": "Rudy",
        "p_nick_333": "Fitzmagic"
      },
      "owner_id": "403029199528394752",
      "player_map": null,
      "players": [
        "7617",
        "8210",
        "1426",
        "1466",
        "9502",
        "9227",
        "3199",
        "503",
        "9490",
        "7528",
        "4098",
        "4454",
        "5927",
        "10223",
        "10236",
        "1476",
        "6770",
        "4177",
        "5248",
        "4993",
        "6945",
        "4981",
        "2750",
        "8132",
        "5987",
        "8408",
        "8117",
        "7564",
        "4082",
        "3634",
        "7496",
        "6083",
        "6111",
        "1373",
        "7608",
        "6927",
        "5995"
      ],
      "reserve": [
        "3199",
        "4454",
        "503",
        "6770",
        "7496"
      ],
      "roster_id": 10,
      "settings": {
        "fpts": 1436,
        "fpts_against": 1532,
        "fpts_against_decimal": 92,
        "fpts_decimal": 34,
        "losses": 9,
        "ppts": 1949,
        "ppts_decimal": 36,
        "rank": 9,
        "ties": 0,
        "total_moves": 0,
        "waiver_budget_used": 0,
        "waiver_position": 6,
        "wins": 5
      },
      "starters": [
        "6111",
        "7528",
        "6945",
        "7564",
        "5927",
        "4981",
        "1466",
        "1426",
        "4098",
        "6083"
      ],
      "taxi": [
        "10223",
        "9227",
        "9490",
        "9502"
      ]
    }
  ],
  "winners_bracket": [
    {
      "m": 1,
      "r": 1,
      "l": 9,
      "w": 1,
      "t1": 1,
      "t2": 9
    },
    {
      "m": 2,
      "r": 1,
      "l": 5,
      "w": 2,
      "t1": 5,
      "t2": 2
    },
    {
      "m": 3,
      "r": 2,
      "l": 1,
      "w": 7,
      "t1": 7,
      "t2": 1,
      "t2_from": {
        "w": 1
      }
    },
    {
      "m": 4,
      "r": 2,
      "l": 6,
      "w": 2,
      "t1": 6,
      "t2": 2,
      "t2_from": {
        "w": 2
      }
    },
    {
      "p": 5,
      "m": 5,
      "r": 2,
      "l": 9,
      "w": 5,
      "t1": 9,
      "t2": 5,
      "t2_from": {
        "l": 2
      },
      "t1_from": {
        "l": 1
      }
    },
    {
      "p": 1,
      "m": 6,
      "r": 3,
      "l": 2,
      "w": 7,
      "t1": 7,
      "t2": 2,
      "t2_from": {
        "w": 4
      },
      "t1_from": {
        "w": 3
      }
    },
    {
      "p": 3,
      "m": 7,
      "r": 3,
      "l": 6,
      "w": 1,
      "t1": 1,
      "t2": 6,
      "t2_from": {
        "l": 4
      },
      "t1_from": {
        "l": 3
      }
    }
  ],
  "loser_bracket": [
    {
      "m": 1,
      "r": 1,
      "l": 8,
      "w": 3,
      "t1": 3,
      "t2": 8
    },
    {
      "m": 2,
      "r": 1,
      "l": 4,
      "w": 10,
      "t1": 4,
      "t2": 10
    },
    {
      "p": 1,
      "m": 3,
      "r": 2,
      "l": 10,
      "w": 3,
      "t1": 3,
      "t2": 10,
      "t2_from": {
        "w": 2
      },
      "t1_from": {
        "w": 1
      }
    },
    {
      "p": 3,
      "m": 4,
      "r": 2,
      "l": 8,
      "w": 4,
      "t1": 8,
      "t2": 4,
      "t2_from": {
        "l": 2
      },
      "t1_from": {
        "l": 1
      }
    }
  ]
}